sharp_frame_extractor/SharpFrameExtractor.py
sharp_frame_extractor/__init__.py
sharp_frame_extractor/__main__.py
sharp_frame_extractor/args_utils.py
sharp_frame_extractor/event.py
sharp_frame_extractor/models.py
sharp_frame_extractor/analyzer/__init__.py
sharp_frame_extractor/analyzer/frame_analyzer_base.py
sharp_frame_extractor/analyzer/frame_analyzer_pool.py
sharp_frame_extractor/analyzer/tenegrad_frame_analyzer.py
sharp_frame_extractor/memory/__init__.py
sharp_frame_extractor/memory/shared_ndarray.py
sharp_frame_extractor/memory/shared_ndarray_pool.py
sharp_frame_extractor/output/__init__.py
sharp_frame_extractor/output/file_output_handler.py
sharp_frame_extractor/output/frame_output_handler_base.py
sharp_frame_extractor/reader/__init__.py
sharp_frame_extractor/reader/av_video_reader.py
sharp_frame_extractor/reader/batched_video_reader.py
sharp_frame_extractor/reader/opencv_video_reader.py
sharp_frame_extractor/reader/video_reader.py
sharp_frame_extractor/ui/__init__.py
sharp_frame_extractor/ui/progress_bar.py
sharp_frame_extractor/worker/BaseWorker.py
sharp_frame_extractor/worker/BaseWorkerPool.py
sharp_frame_extractor/worker/Future.py
sharp_frame_extractor/worker/__init__.py
sharp_frame_extractor/worker/types.py
sharp_frame_extractor-2.0.0.dist-info/licenses/LICENSE
sharp_frame_extractor-2.0.0.dist-info/METADATA
sharp_frame_extractor-2.0.0.dist-info/WHEEL
sharp_frame_extractor-2.0.0.dist-info/entry_points.txt
sharp_frame_extractor-2.0.0.dist-info/top_level.txt
sharp_frame_extractor-2.0.0.dist-info/RECORD
