Metadata-Version: 2.4
Name: sharp-frame-extractor
Version: 2.0.0
Summary: Extracts sharp frames from a video.
Author-email: Florian Bruggisser <github@broox.ch>
License: MIT License
Project-URL: Homepage, https://github.com/cansik/sharp-frame-extractor
Project-URL: Documentation, https://github.com/cansik/sharp-frame-extractor/blob/main/README.md
Project-URL: Repository, https://github.com/cansik/sharp-frame-extractor.git
Classifier: Development Status :: 4 - Beta
Classifier: License :: OSI Approved :: MIT License
Classifier: Intended Audience :: Developers
Classifier: Intended Audience :: Education
Classifier: Intended Audience :: Science/Research
Classifier: Programming Language :: Python :: 3 :: Only
Classifier: Programming Language :: Python :: 3.12
Classifier: Programming Language :: Python :: 3.13
Classifier: Operating System :: MacOS :: MacOS X
Classifier: Operating System :: Microsoft :: Windows
Classifier: Operating System :: POSIX :: Linux
Classifier: Topic :: Multimedia
Classifier: Topic :: Multimedia :: Video
Classifier: Topic :: Scientific/Engineering :: Image Processing
Requires-Python: >=3.12
License-File: LICENSE
Requires-Dist: av>=14.0.1
Requires-Dist: numpy>=2.4.0
Requires-Dist: opencv-python>=4.11.0.86
Requires-Dist: psutil>=7.2.1
Requires-Dist: rich>=14.2.0
Requires-Dist: rich-argparse>=1.7.2
Dynamic: license-file
